topic_specificity/__init__.py
topic_specificity/specificity.py
topic_specificity-0.1.2.dist-info/licenses/LICENSE
topic_specificity-0.1.2.dist-info/METADATA
topic_specificity-0.1.2.dist-info/WHEEL
topic_specificity-0.1.2.dist-info/top_level.txt
topic_specificity-0.1.2.dist-info/RECORD
