Metadata-Version: 2.4
Name: topic-specificity
Version: 0.1.2
Summary: Calculate topic specificity for LDA, LSA & HDP.
Home-page: https://github.com/abigailyuan/topic_specificity
Author: Meng Yuan
Author-email: meng.yuan@unimelb.edu.au
Maintainer: Meng Yuan
Maintainer-email: meng.yuan@unimelb.edu.au
Project-URL: Paper, https://doi.org/10.1145/3578337.3605118
Project-URL: CITATION, https://github.com/abigailyuan/topic_specificity/blob/main/CITATION.cff
Classifier: Programming Language :: Python :: 3
Classifier: License :: OSI Approved :: MIT License
Classifier: Operating System :: OS Independent
Requires-Python: >=3.6
License-File: LICENSE
Requires-Dist: numpy
Requires-Dist: scikit-learn
Dynamic: author
Dynamic: author-email
Dynamic: classifier
Dynamic: description
Dynamic: description-content-type
Dynamic: home-page
Dynamic: license-file
Dynamic: maintainer
Dynamic: maintainer-email
Dynamic: project-url
Dynamic: requires-dist
Dynamic: requires-python
Dynamic: summary
